fluanisotropyanalysis/__init__.py
fluanisotropyanalysis/flu_ani_analysis.py
tests/__init__.py
tests/test_flu_ani_analysis.py
fluanisotropyanalysis-1.0.2.dist-info/LICENSE
fluanisotropyanalysis-1.0.2.dist-info/METADATA
fluanisotropyanalysis-1.0.2.dist-info/WHEEL
fluanisotropyanalysis-1.0.2.dist-info/top_level.txt
fluanisotropyanalysis-1.0.2.dist-info/RECORD
