Metadata-Version: 2.1
Name: fluanisotropyanalysis
Version: 1.0.2
Summary: Read and analyse data from fluorescence anisotropy assays.
Home-page: https://github.com/mariuszlas/Fluorescence-Anisotropy-Analysis
Author: Mariusz Las, Stuart Warriner
Author-email: mariusz.las@protonmail.com, s.l.warriner@leeds.ac.uk
License: UNKNOWN
Platform: UNKNOWN
Classifier: Programming Language :: Python :: 3
Classifier: License :: OSI Approved :: MIT License
Classifier: Operating System :: OS Independent
Requires-Python: >=3.8
License-File: LICENSE
Requires-Dist: platemapping (>=2.0.0)
Requires-Dist: pandas (>=1.1.3)
Requires-Dist: numpy (>=1.19)
Requires-Dist: scipy (>=1.8.0)
Requires-Dist: matplotlib (>=3.5.0)
Requires-Dist: openpyxl (>=3.0.9)
